README.md
setup.cfg
setup.py
smktest/__init__.py
smktest/add.py
smktest/check.py
smktest/create_load_test_file.py
smktest/locust_t00est.py
smktest/scann_api.py
smktest.egg-info/PKG-INFO
smktest.egg-info/SOURCES.txt
smktest.egg-info/dependency_links.txt
smktest.egg-info/requires.txt
smktest.egg-info/top_level.txt