Metadata-Version: 1.2
Name: smktest
Version: 0.1.5
Summary: This package offers a series of tests to create the correct Smoke Test of an application before uploading changes to production.
Home-page: https://github.com/cecilio-cannav/smktest.git
Author: Cecilio Cannavacciuolo Diaz
Author-email: cecilio.cannav@gmail.com
License: MIT
Keywords: smoketest,testing,python,smart
Platform: UNKNOWN
Requires-Python: >=3
